{
    "Name": "DEMON FRENZIED",
    "Level": "1 Harrier Minion",
    "Type": "*Demon, Planar*",
    "EV": "4",
    "Stamina": "8",
    "Weakness": "Holy 3",
    "Speed": "6",
    "Size": "1M / Stability 0",
    "Free Strike": "1",
    "Attributes": {
        "Might": "+0",
        "Agility": "+1",
        "Reason** \u2212": "1",
        "Intuition** \u2212": "1",
        "Presence** \u2212": "1"
    },
    "Abilities": [
        {
            "Name": "Level 1 Harrier Minion**\n*Demon, Planar*\n**EV 4**\n**Stamina**: 8\n**Weakness**: Holy 3\n**Speed**: 6\n**Size**: 1M / Stability 0\n**Free Strike**: 1\n\n- **Might** +0\n- **Agility** +1\n- **Reason** \u22121\n- **Intuition** \u22121\n- **Presence** \u22121\n\n**Rip and Tear (Action)",
            "Details": "**Level 1 Harrier Minion**\n*Demon, Planar*\n**EV 4**\n**Stamina**: 8\n**Weakness**: Holy 3\n**Speed**: 6\n**Size**: 1M / Stability 0\n**Free Strike**: 1\n\n- **Might** +0\n- **Agility** +1\n- **Reason** \u22121\n- **Intuition** \u22121\n- **Presence** \u22121\n\n**Rip and Tear (Action)** \u25c6 2d10 + 1 \u25c6 Signature\nKeywords: Attack, Charge, Melee, Weapon\nDistance: Reach 1\nTarget: One creature or object per minion"
        }
    ]
}